csv2all/__init__.py
csv2all/__main__.py
csv2all-0.0.1600858891.dist-info/METADATA
csv2all-0.0.1600858891.dist-info/WHEEL
csv2all-0.0.1600858891.dist-info/top_level.txt
csv2all-0.0.1600858891.dist-info/RECORD
